dbt_gloss/__init__.py
dbt_gloss/check_column_desc_are_same.py
dbt_gloss/check_column_name_contract.py
dbt_gloss/check_macro_arguments_have_desc.py
dbt_gloss/check_macro_has_description.py
dbt_gloss/check_model_columns_have_desc.py
dbt_gloss/check_model_has_all_columns.py
dbt_gloss/check_model_has_description.py
dbt_gloss/check_model_has_meta_keys.py
dbt_gloss/check_model_has_properties_file.py
dbt_gloss/check_model_has_tests.py
dbt_gloss/check_model_has_tests_by_group.py
dbt_gloss/check_model_has_tests_by_name.py
dbt_gloss/check_model_has_tests_by_type.py
dbt_gloss/check_model_name_contract.py
dbt_gloss/check_model_parents_and_childs.py
dbt_gloss/check_model_parents_database.py
dbt_gloss/check_model_parents_schema.py
dbt_gloss/check_model_tags.py
dbt_gloss/check_script_has_no_table_name.py
dbt_gloss/check_script_ref_and_source.py
dbt_gloss/check_script_semicolon.py
dbt_gloss/check_source_childs.py
dbt_gloss/check_source_columns_have_desc.py
dbt_gloss/check_source_has_all_columns.py
dbt_gloss/check_source_has_freshness.py
dbt_gloss/check_source_has_loader.py
dbt_gloss/check_source_has_meta_keys.py
dbt_gloss/check_source_has_tests.py
dbt_gloss/check_source_has_tests_by_name.py
dbt_gloss/check_source_has_tests_by_type.py
dbt_gloss/check_source_table_has_description.py
dbt_gloss/check_source_tags.py
dbt_gloss/dbt_clean.py
dbt_gloss/dbt_compile.py
dbt_gloss/dbt_deps.py
dbt_gloss/dbt_docs_generate.py
dbt_gloss/dbt_run.py
dbt_gloss/dbt_test.py
dbt_gloss/generate_missing_sources.py
dbt_gloss/generate_model_properties_file.py
dbt_gloss/remove_script_semicolon.py
dbt_gloss/replace_script_table_names.py
dbt_gloss/unify_column_description.py
dbt_gloss/utils.py
dbt_gloss-1.0.0.dist-info/LICENSE
dbt_gloss-1.0.0.dist-info/METADATA
dbt_gloss-1.0.0.dist-info/WHEEL
dbt_gloss-1.0.0.dist-info/entry_points.txt
dbt_gloss-1.0.0.dist-info/top_level.txt
dbt_gloss-1.0.0.dist-info/RECORD
