Metadata-Version: 2.1
Name: dbt-gloss
Version: 1.0.0
Summary: Collection of [pre-commit](https://pre-commit.com) hooks to ensure the quality of your [dbt](https://www.getdbt.com) projects.
Home-page: https://github.com/Montreal-Analytics/dbt-gloss
Author: Montreal Analytics
Author-email: hello@montrealanalytics.com
License: MIT
Platform: UNKNOWN
Classifier: License :: OSI Approved :: MIT License
Classifier: Programming Language :: Python :: 3
Classifier: Programming Language :: Python :: 3 :: Only
Classifier: Programming Language :: Python :: 3.7
Classifier: Programming Language :: Python :: 3.8
Classifier: Programming Language :: Python :: 3.9
Classifier: Programming Language :: Python :: Implementation :: PyPy
Requires-Python: >=3.7.1
License-File: LICENSE
Requires-Dist: pyyaml
